varphi_compiler/CompilationMode.py
varphi_compiler/VarphiCLI.py
varphi_compiler/VarphiDebugAdapter.py
varphi_compiler/__init__.py
varphi_compiler/vpToPy.py
varphi_compiler/vpc.py
varphi_compiler-0.1.6.dist-info/LICENSE
varphi_compiler-0.1.6.dist-info/METADATA
varphi_compiler-0.1.6.dist-info/WHEEL
varphi_compiler-0.1.6.dist-info/entry_points.txt
varphi_compiler-0.1.6.dist-info/top_level.txt
varphi_compiler-0.1.6.dist-info/RECORD
