Metadata-Version: 2.2
Name: varphi_compiler
Version: 0.1.6
Summary: Compiler for the Varphi Programming Language.
Home-page: https://github.com/hassanelsheikha/vpc
Author: Hassan El-Sheikha
Author-email: hassan.elsheikha@utoronto.ca
Classifier: Programming Language :: Python :: 3
Classifier: License :: OSI Approved :: BSD License
Classifier: Operating System :: OS Independent
License-File: LICENSE
Requires-Dist: varphi_parsing_tools==0.0.4
Requires-Dist: pyinstaller
Dynamic: author
Dynamic: author-email
Dynamic: classifier
Dynamic: description
Dynamic: description-content-type
Dynamic: home-page
Dynamic: requires-dist
Dynamic: summary
